{
  "0": {
    "$type": "number",
    "$value": 0,
    "$extensions": {
      "com.figma.variableId": "VariableID:9:27",
      "com.figma.scopes": [
        "ALL_SCOPES"
      ]
    }
  },
  "4": {
    "$type": "number",
    "$value": 4,
    "$extensions": {
      "com.figma.variableId": "VariableID:9:28",
      "com.figma.scopes": [
        "ALL_SCOPES"
      ]
    }
  },
  "8": {
    "$type": "number",
    "$value": 8,
    "$extensions": {
      "com.figma.variableId": "VariableID:9:29",
      "com.figma.scopes": [
        "ALL_SCOPES"
      ]
    }
  },
  "10": {
    "$type": "number",
    "$value": 10,
    "$extensions": {
      "com.figma.variableId": "VariableID:13:8",
      "com.figma.scopes": [
        "ALL_SCOPES"
      ]
    }
  },
  "12": {
    "$type": "number",
    "$value": 12,
    "$extensions": {
      "com.figma.variableId": "VariableID:9:30",
      "com.figma.scopes": [
        "ALL_SCOPES"
      ]
    }
  },
  "16": {
    "$type": "number",
    "$value": 16,
    "$extensions": {
      "com.figma.variableId": "VariableID:9:31",
      "com.figma.scopes": [
        "ALL_SCOPES"
      ]
    }
  },
  "20": {
    "$type": "number",
    "$value": 20,
    "$extensions": {
      "com.figma.variableId": "VariableID:9:32",
      "com.figma.scopes": [
        "ALL_SCOPES"
      ]
    }
  },
  "24": {
    "$type": "number",
    "$value": 24,
    "$extensions": {
      "com.figma.variableId": "VariableID:9:33",
      "com.figma.scopes": [
        "ALL_SCOPES"
      ]
    }
  },
  "28": {
    "$type": "number",
    "$value": 28,
    "$extensions": {
      "com.figma.variableId": "VariableID:9:34",
      "com.figma.scopes": [
        "ALL_SCOPES"
      ]
    }
  },
  "32": {
    "$type": "number",
    "$value": 32,
    "$extensions": {
      "com.figma.variableId": "VariableID:9:35",
      "com.figma.scopes": [
        "ALL_SCOPES"
      ]
    }
  },
  "$extensions": {
    "com.figma.modeName": "Mode 1"
  }
}